{
    "key": "ui_options_page_69c6efb8299c2",
    "title": "Cabildo",
    "active": true,
    "menu_order": 0,
    "page_title": "Cabildo",
    "menu_slug": "cabildo",
    "parent_slug": "none",
    "advanced_configuration": 1,
    "icon_url": "",
    "menu_title": "",
    "position": 4,
    "redirect": 0,
    "description": "",
    "menu_icon": {
        "type": "dashicons",
        "value": "dashicons-businessman"
    },
    "update_button": "Actualizar",
    "updated_message": "Opciones Actualizadas",
    "capability": "edit_posts",
    "data_storage": "options",
    "post_id": "",
    "autoload": 0,
    "modified": 1775512863
}
